{
  "colorChartsStatusCritical": {
    "description": "Color to represent a critical error or a critically high-level of severity. For example: \"Sev-1\""
  },
  "colorChartsStatusHigh": {
    "description": "Color to represent an error status or a high-level of severity. Use this color to represent a default error status when there is only one applicable to a chart. For example: \"Failed\" or \"Sev-2\""
  },
  "colorChartsStatusMedium": {
    "description": "Color to represent a medium-level of severity. For example: \"Sev-3\""
  },
  "colorChartsStatusLow": {
    "description": "Color to represent a warning or a low-level of severity. For example: \"Warning\" or \"Sev-4\""
  },
  "colorChartsStatusPositive": {
    "description": "Color to represent a positive status. *For example: \"Success\" or \"Running\""
  },
  "colorChartsStatusInfo": {
    "description": "Color to represent an informational status. For example: \"In-progress\" or \"Updating\""
  },
  "colorChartsStatusNeutral": {
    "description": "Color to represent a neutral status, a severity level of no impact, or the lowest-level of severity. For example: \"Pending\" or \"Sev-5\""
  },
  "colorChartsThresholdNegative": {
    "description": "The color to represent a threshold with a negative outcome. For example: A maximum limit"
  },
  "colorChartsThresholdPositive": {
    "description": "The color to represent a threshold with a positive outcome. For example: A designated pass rate"
  },
  "colorChartsThresholdInfo": {
    "description": "The color to represent an informational threshold to highlight special circumstances that may have or will occur. For example: A forecasted estimate"
  },
  "colorChartsThresholdNeutral": {
    "description": "The color to represent a threshold with a neutral outcome. For example: An average or baseline"
  },
  "colorChartsPaletteCategorical1": {
    "description": "Color #1 on the categorical data visualization palette."
  },
  "colorChartsPaletteCategorical2": {
    "description": "Color #2 on the categorical data visualization palette."
  },
  "colorChartsPaletteCategorical3": {
    "description": "Color #3 on the categorical data visualization palette."
  },
  "colorChartsPaletteCategorical4": {
    "description": "Color #4 on the categorical data visualization palette."
  },
  "colorChartsPaletteCategorical5": {
    "description": "Color #5 on the categorical data visualization palette."
  },
  "colorChartsPaletteCategorical6": {
    "description": "Color #6 on the categorical data visualization palette."
  },
  "colorChartsPaletteCategorical7": {
    "description": "Color #7 on the categorical data visualization palette."
  },
  "colorChartsPaletteCategorical8": {
    "description": "Color #8 on the categorical data visualization palette."
  },
  "colorChartsPaletteCategorical9": {
    "description": "Color #9 on the categorical data visualization palette."
  },
  "colorChartsPaletteCategorical10": {
    "description": "Color #10 on the categorical data visualization palette."
  },
  "colorChartsPaletteCategorical11": {
    "description": "Color #11 on the categorical data visualization palette."
  },
  "colorChartsPaletteCategorical12": {
    "description": "Color #12 on the categorical data visualization palette."
  },
  "colorChartsPaletteCategorical13": {
    "description": "Color #13 on the categorical data visualization palette."
  },
  "colorChartsPaletteCategorical14": {
    "description": "Color #14 on the categorical data visualization palette."
  },
  "colorChartsPaletteCategorical15": {
    "description": "Color #15 on the categorical data visualization palette."
  },
  "colorChartsPaletteCategorical16": {
    "description": "Color #16 on the categorical data visualization palette."
  },
  "colorChartsPaletteCategorical17": {
    "description": "Color #17 on the categorical data visualization palette."
  },
  "colorChartsPaletteCategorical18": {
    "description": "Color #18 on the categorical data visualization palette."
  },
  "colorChartsPaletteCategorical19": {
    "description": "Color #19 on the categorical data visualization palette."
  },
  "colorChartsPaletteCategorical20": {
    "description": "Color #20 on the categorical data visualization palette."
  },
  "colorChartsPaletteCategorical21": {
    "description": "Color #21 on the categorical data visualization palette."
  },
  "colorChartsPaletteCategorical22": {
    "description": "Color #22 on the categorical data visualization palette."
  },
  "colorChartsPaletteCategorical23": {
    "description": "Color #23 on the categorical data visualization palette."
  },
  "colorChartsPaletteCategorical24": {
    "description": "Color #24 on the categorical data visualization palette."
  },
  "colorChartsPaletteCategorical25": {
    "description": "Color #25 on the categorical data visualization palette."
  },
  "colorChartsPaletteCategorical26": {
    "description": "Color #26 on the categorical data visualization palette."
  },
  "colorChartsPaletteCategorical27": {
    "description": "Color #27 on the categorical data visualization palette."
  },
  "colorChartsPaletteCategorical28": {
    "description": "Color #28 on the categorical data visualization palette."
  },
  "colorChartsPaletteCategorical29": {
    "description": "Color #29 on the categorical data visualization palette."
  },
  "colorChartsPaletteCategorical30": {
    "description": "Color #30 on the categorical data visualization palette."
  },
  "colorChartsPaletteCategorical31": {
    "description": "Color #31 on the categorical data visualization palette."
  },
  "colorChartsPaletteCategorical32": {
    "description": "Color #32 on the categorical data visualization palette."
  },
  "colorChartsPaletteCategorical33": {
    "description": "Color #33 on the categorical data visualization palette."
  },
  "colorChartsPaletteCategorical34": {
    "description": "Color #34 on the categorical data visualization palette."
  },
  "colorChartsPaletteCategorical35": {
    "description": "Color #35 on the categorical data visualization palette."
  },
  "colorChartsPaletteCategorical36": {
    "description": "Color #36 on the categorical data visualization palette."
  },
  "colorChartsPaletteCategorical37": {
    "description": "Color #37 on the categorical data visualization palette."
  },
  "colorChartsPaletteCategorical38": {
    "description": "Color #38 on the categorical data visualization palette."
  },
  "colorChartsPaletteCategorical39": {
    "description": "Color #39 on the categorical data visualization palette."
  },
  "colorChartsPaletteCategorical40": {
    "description": "Color #40 on the categorical data visualization palette."
  },
  "colorChartsPaletteCategorical41": {
    "description": "Color #41 on the categorical data visualization palette."
  },
  "colorChartsPaletteCategorical42": {
    "description": "Color #42 on the categorical data visualization palette."
  },
  "colorChartsPaletteCategorical43": {
    "description": "Color #43 on the categorical data visualization palette."
  },
  "colorChartsPaletteCategorical44": {
    "description": "Color #44 on the categorical data visualization palette."
  },
  "colorChartsPaletteCategorical45": {
    "description": "Color #45 on the categorical data visualization palette."
  },
  "colorChartsPaletteCategorical46": {
    "description": "Color #46 on the categorical data visualization palette."
  },
  "colorChartsPaletteCategorical47": {
    "description": "Color #47 on the categorical data visualization palette."
  },
  "colorChartsPaletteCategorical48": {
    "description": "Color #48 on the categorical data visualization palette."
  },
  "colorChartsPaletteCategorical49": {
    "description": "Color #49 on the categorical data visualization palette."
  },
  "colorChartsPaletteCategorical50": {
    "description": "Color #50 on the categorical data visualization palette."
  },
  "colorBackgroundButtonPrimaryActive": {
    "description": "The background color of primary buttons in active state."
  },
  "colorBackgroundButtonPrimaryDefault": {
    "description": "The default background color of primary buttons."
  },
  "colorBackgroundButtonPrimaryDisabled": {
    "description": "The background color of primary buttons in disabled state."
  },
  "colorBackgroundButtonPrimaryHover": {
    "description": "The background color of primary buttons in hover state."
  },
  "colorBackgroundCellShaded": {
    "description": "The background color of shaded table cells."
  },
  "colorBackgroundContainerContent": {
    "description": "The background color of container main content areas. For example: content areas of form sections, containers, tables, and cards."
  },
  "colorBackgroundContainerHeader": {
    "description": "The background color of container headers. For example: headers of form sections, containers, tables, and card collections."
  },
  "colorBackgroundControlChecked": {
    "description": "The background color of a checked form control. For example: background fill of a selected radio button, checked checkbox, and toggle that is switched on."
  },
  "colorBackgroundControlDefault": {
    "description": "The default background color of form controls. For example: radio buttons and checkboxes default background fill color."
  },
  "colorBackgroundControlDisabled": {
    "description": "The background color of a disabled form control. For example: background fill of a disabled radio button and checkbox."
  },
  "colorBackgroundDropdownItemDefault": {
    "description": "The default background color of dropdown items. For example: select, multiselect, autosuggest, and datepicker dropdown backgrounds."
  },
  "colorBackgroundDropdownItemFilterMatch": {
    "description": "The background color of text that matches a user's query. For example: the background of text matching a query entered into a table filter, select, multiselect, or autosuggest."
  },
  "colorBackgroundDropdownItemHover": {
    "description": "The background color of dropdown items on hover. For example: background of hovered items in select, multiselect, autosuggest, and datepicker dropdowns."
  },
  "colorBackgroundHomeHeader": {
    "description": "The background color of the home header, displayed on the Service's home page."
  },
  "colorBackgroundInputDefault": {
    "description": "The default background color of form inputs. For example: background fill of an input, textarea, autosuggest, and trigger of a select and multiselect."
  },
  "colorBackgroundInputDisabled": {
    "description": "The background color of a disabled form input. For example: background fill of a disabled input, textarea, autosuggest, and trigger of a select and multiselect."
  },
  "colorBackgroundItemSelected": {
    "description": "The background color of a selected item. For example: tokens, selected table rows, cards, and tile backgrounds."
  },
  "colorBackgroundLayoutMain": {
    "description": "The background color of the main content area on a page. For example:  content area in app layout."
  },
  "colorBackgroundLayoutToggleActive": {
    "description": "The background color of the app layout toggle button when it's active."
  },
  "colorBackgroundLayoutToggleDefault": {
    "description": "The default background color of the app layout toggle button."
  },
  "colorBackgroundLayoutToggleHover": {
    "description": "The background color of the app layout toggle button on hover."
  },
  "colorBackgroundLayoutToggleSelectedActive": {
    "description": "The background color of the app layout toggle button when it's selected and active."
  },
  "colorBackgroundLayoutToggleSelectedDefault": {
    "description": "The default background color of the app layout toggle button when it's selected."
  },
  "colorBackgroundLayoutToggleSelectedHover": {
    "description": "The background color of the app layout toggle button on hover when it's selected."
  },
  "colorBackgroundNotificationBlue": {
    "description": "Background color for blue notifications. For example: blue badges and info flash messages."
  },
  "colorBackgroundNotificationGreen": {
    "description": "Background color for green notifications. For example: green badges and success flash messages."
  },
  "colorBackgroundNotificationRed": {
    "description": "Background color for red notifications. For example: red badges and error flash messages."
  },
  "colorBackgroundStatusError": {
    "description": "The background color of an item in error state. For example: error alerts."
  },
  "colorBackgroundStatusInfo": {
    "description": "The background color of an informational item. For example: information alerts."
  },
  "colorBackgroundStatusSuccess": {
    "description": "The background color of an item in success state. For example: success alerts."
  },
  "colorBackgroundStatusWarning": {
    "description": "The background color of an item in warning state. For example: warning alerts."
  },
  "colorBackgroundToggleCheckedDisabled": {
    "description": "The background color of checked toggles in disabled state."
  },
  "colorBorderButtonNormalDefault": {
    "description": "The border color of normal buttons."
  },
  "colorBorderButtonNormalDisabled": {
    "description": "The border color of normal buttons in disabled state."
  },
  "colorBorderButtonNormalHover": {
    "description": "The border color of normal buttons in hover state."
  },
  "colorBorderButtonPrimaryDisabled": {
    "description": "The border color of primary buttons in disabled state."
  },
  "colorBorderContainerTop": {
    "description": "The top border color for containers and first item in dropdowns. For example: the top border of a card, dropdown, and table."
  },
  "colorBorderControlDefault": {
    "description": "The default border color of form controls. For example: radio buttons and checkboxes."
  },
  "colorBorderDividerDefault": {
    "description": "The default color for dividers. For example: dividers in column layout, expanding sections, side nav, help panel, between table rows and dropdown items, and inside containers."
  },
  "colorBorderDropdownItemHover": {
    "description": "The border color of dropdown items on hover. For example: border of hovered items in select, multiselect, autosuggest, and hovered days in datepicker."
  },
  "colorBorderInputDefault": {
    "description": "The default border color of form inputs. For example: input, textarea, autosuggest, datepicker, select, and multiselect."
  },
  "colorBorderItemFocused": {
    "description": "The color of focus states. For example: the focus ring around interactive elements."
  },
  "colorBorderItemSelected": {
    "description": "The border color of a selected item. For example: tokens, selected table rows, selected cards, and selected tile borders."
  },
  "colorBorderStatusError": {
    "description": "The border color of an item in error state. For example: error alerts."
  },
  "colorBorderStatusInfo": {
    "description": "The border color of an informational item. For example: information alerts."
  },
  "colorBorderStatusSuccess": {
    "description": "The border color of an item in success state. For example: success alerts."
  },
  "colorBorderStatusWarning": {
    "description": "The border color of an item in warning state. For example: warning alerts."
  },
  "colorForegroundControlDefault": {
    "description": "The color used to mark enabled form controls. For example: the checkmark on checkboxes, inner circle on radio buttons, and handle on toggles."
  },
  "colorForegroundControlDisabled": {
    "description": "The color used to mark disabled form controls. For example: the checkmark on checkboxes, inner circle on radio buttons, and handle on toggles."
  },
  "colorTextAccent": {
    "description": "The accent color used to guide a user. *For example: the highlighted page in the side navigation and active tab text.*"
  },
  "colorTextBodyDefault": {
    "description": "The default color of non-heading text and body content. For example: text in a paragraph tag, table cell data, form field labels and values."
  },
  "colorTextBodySecondary": {
    "description": "The color of text that is secondary to base text. For example: text in the navigation and tools panels."
  },
  "colorTextButtonNormalActive": {
    "description": "The active text color of normal buttons. For example: Active text color in normal and link buttons."
  },
  "colorTextButtonNormalDefault": {
    "description": "The default text color of normal buttons."
  },
  "colorTextButtonNormalHover": {
    "description": "The hover text color of normal buttons."
  },
  "colorTextButtonPrimaryActive": {
    "description": "The active text color of primary buttons."
  },
  "colorTextButtonPrimaryDefault": {
    "description": "The default text color of primary buttons."
  },
  "colorTextButtonPrimaryHover": {
    "description": "The hover text color of primary buttons."
  },
  "colorTextCounter": {
    "description": "The default color for counters. For example: counters in table headers"
  },
  "colorTextDropdownItemFilterMatch": {
    "description": "The color of text matching a user's query. For example: the text matching a query entered into a table filter, select, multiselect, or autosuggest."
  },
  "colorTextDropdownItemHighlighted": {
    "description": "The text color of hovered or selected dropdown items. *For example: selected day text color in date picker, label text color of the item on hover in a select, multiselect, and autosuggest.*"
  },
  "colorTextEmpty": {
    "description": "The color of text in non-dropdown empty states. For example: tables, card collections, and attribute editor empty state text."
  },
  "colorTextFormDefault": {
    "description": "The default color of form field labels and values. For example: the label in form fields, checkboxes, radio buttons, toggles, and the value in inputs and text areas."
  },
  "colorTextFormSecondary": {
    "description": "The color of secondary text in form fields and controls. For example: the description and constraint text in form fields, the descriptions in checkboxes, radio buttons, toggles, and any additional info in an attribute editor."
  },
  "colorTextGroupLabel": {
    "description": "The default color for group labels. For example: group label in dropdown part of button dropdown, select, and multiselect, and group label in table and cards' preferences content selector."
  },
  "colorTextHeadingDefault": {
    "description": "The default color for headings 1-5. For example: headings in tables, card collections, containers, form sections, forms, and app layout panels."
  },
  "colorTextHeadingSecondary": {
    "description": "The default color for secondary heading text such as page and container descriptions. For example: descriptions in containers such as form sections, tables, and card collections, as well as form page descriptions."
  },
  "colorTextHomeHeaderDefault": {
    "description": "The color of the home header's text, displayed on the Service's home page."
  },
  "colorTextHomeHeaderSecondary": {
    "description": "The color of the home header's secondary text, displayed on the Service's home page."
  },
  "colorTextInputDisabled": {
    "description": "The color of the text value in a disabled input. For example: text in a disabled input, autosuggest, datepicker, and the trigger of a select and multiselect."
  },
  "colorTextInputPlaceholder": {
    "description": "The color of placeholder text in an input. For example: placeholder text in an input, autosuggest, datepicker, and the trigger of a select and multiselect."
  },
  "colorTextInteractiveActive": {
    "description": "The color of clickable elements in their active state. For example: tabs and icons."
  },
  "colorTextInteractiveDefault": {
    "description": "The color of clickable elements in their default state. *For example: expandable sections, tabs, and icons.*"
  },
  "colorTextInteractiveDisabled": {
    "description": "The color of clickable elements in their disabled state. For example: disabled tabs, button text, and icons."
  },
  "colorTextInteractiveHover": {
    "description": "The color of clickable elements on hover. *For example: expandable sections, and icons on hover.*"
  },
  "colorTextInteractiveInvertedDefault": {
    "description": "The default color of clickable elements in the flashbar. For example: The dismiss icon button in a flashbar."
  },
  "colorTextInteractiveInvertedHover": {
    "description": "The hover color of clickable elements in the flashbar. For example: The dismiss icon button in a flashbar."
  },
  "colorTextLabel": {
    "description": "This is the default color for non-form labels. For example: the key in key/value pairs and card's sections labels."
  },
  "colorTextLinkDefault": {
    "description": "The default color for links. For example: text in an anchor tag, info links, breadcrumb links, and icon links."
  },
  "colorTextLinkHover": {
    "description": "The hover color for links. For example: text in an anchor tag, info links, breadcrumb links, and icon links."
  },
  "colorTextNotificationDefault": {
    "description": "Default text color for notifications. For example: the text on badges and flashes."
  },
  "colorTextStatusError": {
    "description": "The color of error text and icons. For example: form field error text and error status indicators."
  },
  "colorTextStatusInactive": {
    "description": "The color of inactive and loading text and icons. For example: table and card collection loading states icon and text and inactive and pending status indicators."
  },
  "colorTextStatusInfo": {
    "description": "The color of info text and icons. For example: info status indicators and info alert icon."
  },
  "colorTextStatusSuccess": {
    "description": "The color of success text and icons. For example: success status indicators and success alert icon."
  },
  "colorTextStatusWarning": {
    "description": "The color of warning icons."
  },
  "colorTextTopNavigationTitle": {
    "description": "The color of the title in the top navigation."
  },
  "fontFamilyBase": {
    "description": "The default font family that will be applied globally to the product interface. "
  },
  "fontFamilyMonospace": {
    "description": "The monospace font family that will be applied globally to the product interface."
  },
  "borderRadiusAlert": {
    "description": "The border radius of alerts."
  },
  "borderRadiusBadge": {
    "description": "The border radius of badges."
  },
  "borderRadiusButton": {
    "description": "The border radius of buttons and segmented control's segments."
  },
  "borderRadiusCalendarDayFocusRing": {
    "description": "The border radius of the focused day in date picker and date range picker."
  },
  "borderRadiusContainer": {
    "description": "The border radius of containers. Also used in container-based components like table, cards, expandable section, and modal."
  },
  "borderRadiusControlCircularFocusRing": {
    "description": "The border radius of the focus indicator of circular controls. For example: radio button."
  },
  "borderRadiusControlDefaultFocusRing": {
    "description": "The border radius of the focus indicator of interactive elements. For example: button, link, toggle, pagination controls, expandable section header, popover trigger."
  },
  "borderRadiusDropdown": {
    "description": "The border radius of dropdown containers. For example: button dropdown, select, multiselect, autosuggest, date picker, date range picker."
  },
  "borderRadiusFlashbar": {
    "description": "The border radius of flash messages in flashbars."
  },
  "borderRadiusItem": {
    "description": "The border radius of items that can be selected from a list. For example: select options, table rows, calendar days."
  },
  "borderRadiusInput": {
    "description": "The border radius of form controls. For example: input, select."
  },
  "borderRadiusPopover": {
    "description": "The border radius of popovers."
  },
  "borderRadiusTabsFocusRing": {
    "description": "The border radius of tabs' focus indicator. Used in tabs and in the code editor status bar."
  },
  "borderRadiusTiles": {
    "description": "The border radius of tiles."
  },
  "borderRadiusToken": {
    "description": "The border radius of tokens. For example: token groups, multiselect tokens, property filter tokens."
  },
  "borderRadiusTutorialPanelItem": {
    "description": "The border radius of tutorials inside a tutorial panel."
  }
}